setup.py
runtimestamp/__init__.py
runtimestamp/runtimestamp.py
runtimestamp.egg-info/PKG-INFO
runtimestamp.egg-info/SOURCES.txt
runtimestamp.egg-info/dependency_links.txt
runtimestamp.egg-info/top_level.txt