Metadata-Version: 1.0
Name: runtimestamp
Version: 0.0.2
Summary: Leaves an timestamp and signature at the top of every notebook
Home-page: https://github.com/yinleon/runtimestamp
Author: leon yin
Author-email: ly501@nyu.edu
License: MIT
Keywords: jupyter notebook,timestamp
Platform: UNKNOWN
